alloy/__init__.py
alloy/batch.py
alloy/benchmark.py
alloy/cli.py
alloy/converter.py
alloy/flux_converter.py
alloy/flux_runner.py
alloy/hf_utils.py
alloy/hunyuan_converter.py
alloy/hunyuan_runner.py
alloy/ltx_converter.py
alloy/ltx_runner.py
alloy/lumina_converter.py
alloy/lumina_runner.py
alloy/model_utils.py
alloy/runner.py
alloy/utils.py
alloy/wan_converter.py
silicon_alloy-0.2.2.dist-info/METADATA
silicon_alloy-0.2.2.dist-info/WHEEL
silicon_alloy-0.2.2.dist-info/entry_points.txt
silicon_alloy-0.2.2.dist-info/licenses/LICENSE
silicon_alloy-0.2.2.dist-info/RECORD
