Metadata-Version: 2.4
Name: silicon-alloy
Version: 0.2.2
Summary: High-performance Core ML diffusion toolchain for Apple Silicon
Project-URL: Homepage, https://github.com/hybridindie/alloy
Project-URL: Documentation, https://github.com/hybridindie/alloy#readme
Project-URL: Repository, https://github.com/hybridindie/alloy
Project-URL: Issues, https://github.com/hybridindie/alloy/issues
Author-email: John Dilts <john@hybridindie.com>
Maintainer-email: John Dilts <john@hybridindie.com>
License: MIT
License-File: LICENSE
Keywords: apple-silicon,core-ml,diffusion,flux,ltx-video,machine-learning
Classifier: Development Status :: 4 - Beta
Classifier: Intended Audience :: Developers
Classifier: Intended Audience :: Science/Research
Classifier: License :: OSI Approved :: MIT License
Classifier: Operating System :: MacOS :: MacOS X
Classifier: Programming Language :: Python :: 3
Classifier: Programming Language :: Python :: 3.11
Classifier: Programming Language :: Python :: 3.12
Classifier: Topic :: Scientific/Engineering :: Artificial Intelligence
Classifier: Topic :: Software Development :: Libraries :: Python Modules
Requires-Python: >=3.11
Requires-Dist: accelerate
Requires-Dist: coremltools>=8.0
Requires-Dist: diffusers[torch]>=0.30.0
Requires-Dist: huggingface-hub>=0.24.0
Requires-Dist: matplotlib
Requires-Dist: numpy<2.0.0
Requires-Dist: psutil
Requires-Dist: python-dotenv
Requires-Dist: pyyaml
Requires-Dist: rich
Requires-Dist: safetensors>=0.4.0
Requires-Dist: scikit-learn
Requires-Dist: scipy
Requires-Dist: sentencepiece
Requires-Dist: torch>=2.4.0
Requires-Dist: tqdm
Requires-Dist: transformers>=4.44.0
